orgutils/__init__.py
orgutils/orgutils.py
orgutils-0.0.7.dist-info/LICENCE
orgutils-0.0.7.dist-info/METADATA
orgutils-0.0.7.dist-info/WHEEL
orgutils-0.0.7.dist-info/top_level.txt
orgutils-0.0.7.dist-info/RECORD
